mcpower_shared/__init__.py
mcpower_shared/mcp_types.py
mcpower_shared-0.1.5.dist-info/licenses/LICENSE
mcpower_shared-0.1.5.dist-info/METADATA
mcpower_shared-0.1.5.dist-info/WHEEL
mcpower_shared-0.1.5.dist-info/top_level.txt
mcpower_shared-0.1.5.dist-info/RECORD
