Metadata-Version: 2.4
Name: mcpower_shared
Version: 0.1.5
Summary: Shared types and utilities for MCPower projects
Author: MCPower
License-Expression: Apache-2.0
Project-URL: Homepage, https://github.com/MCPower-Security/mcpower-shared
Project-URL: Repository, https://github.com/MCPower-Security/mcpower-shared
Project-URL: Issues, https://github.com/MCPower-Security/mcpower-shared/issues
Classifier: Development Status :: 3 - Alpha
Classifier: Intended Audience :: Developers
Classifier: Programming Language :: Python :: 3
Classifier: Programming Language :: Python :: 3.10
Classifier: Programming Language :: Python :: 3.11
Classifier: Programming Language :: Python :: 3.12
Requires-Python: >=3.10
License-File: LICENSE
Dynamic: license-file
